spacelog/SpaceLogClient.py
spacelog/SpaceLogCounter.py
spacelog/__init__.py
space_log-0.2.0.dist-info/METADATA
space_log-0.2.0.dist-info/WHEEL
space_log-0.2.0.dist-info/top_level.txt
space_log-0.2.0.dist-info/RECORD
