Metadata-Version: 2.1
Name: space-log
Version: 0.2.0
Summary: Space-log is a simple event logging system.
Home-page: https://github.com/cansik/space-log
Author: Florian Bruggisser
Author-email: github@broox.ch
License: MIT License
Requires-Dist: requests
Requires-Dist: python-dateutil~=2.9.0
